RCAIDE/Vehicle.py
RCAIDE/__init__.py
RCAIDE/load.py
RCAIDE/save.py
RCAIDE/version.py
RCAIDE/Framework/__init__.py
RCAIDE/Framework/Analyses/Analysis.py
RCAIDE/Framework/Analyses/Process.py
RCAIDE/Framework/Analyses/Settings.py
RCAIDE/Framework/Analyses/Vehicle.py
RCAIDE/Framework/Analyses/__init__.py
RCAIDE/Framework/Analyses/Aerodynamics/Aerodynamics.py
RCAIDE/Framework/Analyses/Aerodynamics/Vortex_Lattice_Method.py
RCAIDE/Framework/Analyses/Aerodynamics/__init__.py
RCAIDE/Framework/Analyses/Atmospheric/__init__.py
RCAIDE/Framework/Analyses/Common/Process_Geometry.py
RCAIDE/Framework/Analyses/Common/__init__.py
RCAIDE/Framework/Analyses/Costs/Costs.py
RCAIDE/Framework/Analyses/Costs/__init__.py
RCAIDE/Framework/Analyses/Emissions/Emission_Index_Correlation_Method.py
RCAIDE/Framework/Analyses/Emissions/Emissions.py
RCAIDE/Framework/Analyses/Emissions/__init__.py
RCAIDE/Framework/Analyses/Energy/Energy.py
RCAIDE/Framework/Analyses/Energy/__init__.py
RCAIDE/Framework/Analyses/Noise/Correlation_Buildup.py
RCAIDE/Framework/Analyses/Noise/Frequency_Domain_Buildup.py
RCAIDE/Framework/Analyses/Noise/Noise.py
RCAIDE/Framework/Analyses/Noise/__init__.py
RCAIDE/Framework/Analyses/Planets/__init__.py
RCAIDE/Framework/Analyses/Propulsion/__init__.py
RCAIDE/Framework/Analyses/Stability/Stability.py
RCAIDE/Framework/Analyses/Stability/Vortex_Lattice_Method.py
RCAIDE/Framework/Analyses/Stability/__init__.py
RCAIDE/Framework/Analyses/Weights/__init__.py
RCAIDE/Framework/Core/Arrays.py
RCAIDE/Framework/Core/Container.py
RCAIDE/Framework/Core/Utilities.py
RCAIDE/Framework/Core/__init__.py
RCAIDE/Framework/External_Interfaces/__init__.py
RCAIDE/Framework/External_Interfaces/OpenVSP/__init__.py
RCAIDE/Framework/Mission/Missions.py
RCAIDE/Framework/Mission/Sequential_Segments.py
RCAIDE/Framework/Mission/__init__.py
RCAIDE/Framework/Mission/Common/Conditions.py
RCAIDE/Framework/Mission/Common/Numerics.py
RCAIDE/Framework/Mission/Common/Residuals.py
rcaide_sai-24.1.0.dist-info/LICENSE
rcaide_sai-24.1.0.dist-info/METADATA
rcaide_sai-24.1.0.dist-info/WHEEL
rcaide_sai-24.1.0.dist-info/top_level.txt
rcaide_sai-24.1.0.dist-info/RECORD
